cdktf_cdktf_provider_spotinst/__init__.py
cdktf_cdktf_provider_spotinst/py.typed
cdktf_cdktf_provider_spotinst/_jsii/__init__.py
cdktf_cdktf_provider_spotinst/_jsii/provider-spotinst@14.9.0.jsii.tgz
cdktf_cdktf_provider_spotinst/account/__init__.py
cdktf_cdktf_provider_spotinst/account_aws/__init__.py
cdktf_cdktf_provider_spotinst/credentials_aws/__init__.py
cdktf_cdktf_provider_spotinst/credentials_azure/__init__.py
cdktf_cdktf_provider_spotinst/credentials_gcp/__init__.py
cdktf_cdktf_provider_spotinst/data_integration/__init__.py
cdktf_cdktf_provider_spotinst/elastigroup_aws/__init__.py
cdktf_cdktf_provider_spotinst/elastigroup_aws_beanstalk/__init__.py
cdktf_cdktf_provider_spotinst/elastigroup_aws_suspension/__init__.py
cdktf_cdktf_provider_spotinst/elastigroup_azure_v3/__init__.py
cdktf_cdktf_provider_spotinst/elastigroup_gcp/__init__.py
cdktf_cdktf_provider_spotinst/elastigroup_gke/__init__.py
cdktf_cdktf_provider_spotinst/health_check/__init__.py
cdktf_cdktf_provider_spotinst/managed_instance_aws/__init__.py
cdktf_cdktf_provider_spotinst/mrscaler_aws/__init__.py
cdktf_cdktf_provider_spotinst/notification_center/__init__.py
cdktf_cdktf_provider_spotinst/ocean_aks_np/__init__.py
cdktf_cdktf_provider_spotinst/ocean_aks_np_virtual_node_group/__init__.py
cdktf_cdktf_provider_spotinst/ocean_aws/__init__.py
cdktf_cdktf_provider_spotinst/ocean_aws_extended_resource_definition/__init__.py
cdktf_cdktf_provider_spotinst/ocean_aws_launch_spec/__init__.py
cdktf_cdktf_provider_spotinst/ocean_ecs/__init__.py
cdktf_cdktf_provider_spotinst/ocean_ecs_launch_spec/__init__.py
cdktf_cdktf_provider_spotinst/ocean_gke_import/__init__.py
cdktf_cdktf_provider_spotinst/ocean_gke_launch_spec/__init__.py
cdktf_cdktf_provider_spotinst/ocean_gke_launch_spec_import/__init__.py
cdktf_cdktf_provider_spotinst/ocean_right_sizing_rule/__init__.py
cdktf_cdktf_provider_spotinst/ocean_spark/__init__.py
cdktf_cdktf_provider_spotinst/ocean_spark_virtual_node_group/__init__.py
cdktf_cdktf_provider_spotinst-14.9.0.dist-info/LICENSE
cdktf_cdktf_provider_spotinst-14.9.0.dist-info/METADATA
cdktf_cdktf_provider_spotinst-14.9.0.dist-info/WHEEL
cdktf_cdktf_provider_spotinst-14.9.0.dist-info/top_level.txt
cdktf_cdktf_provider_spotinst-14.9.0.dist-info/RECORD
